dataferry/__init__.py
dataferry/connections.py
dataferry/dimensions.py
dataferry/execution.py
dataferry/functions.py
dataferry/transfers.py
dataferry_etl-0.0.8.dist-info/LICENSE
dataferry_etl-0.0.8.dist-info/METADATA
dataferry_etl-0.0.8.dist-info/WHEEL
dataferry_etl-0.0.8.dist-info/top_level.txt
dataferry_etl-0.0.8.dist-info/RECORD
