Metadata-Version: 2.1
Name: dataferry-etl
Version: 0.0.8
Summary: Simple ETL tools and functions for SQL Server
Author: Porte Verte
Author-email: Port Verte <porte_verte@outlook.com>
Classifier: Programming Language :: Python :: 3
Classifier: License :: OSI Approved :: MIT License
Classifier: Operating System :: OS Independent
Requires-Python: >=3.8
License-File: LICENSE
